[
    {
      "id": "2hsfhs34vj",
      "name": "CryptoFunks",
      "eth": "19,769.39",
      "time": "25",
      "img": "https://media.istockphoto.com/id/1463455851/photo/cryptocurrency-market-financial-data-and-candlesticks-internet-banking.jpg?s=2048x2048&w=is&k=20&c=yMVz_O_vreaVKAmvjWbwUd1sowqQOshuhqOnBNbUy50=",
      "logo1": "https://i.ibb.co/F8H3Pmf/Ellipse-95-4.png",
      "logo2": "https://i.ibb.co/mNtcFR8/Ellipse-95-3.png",
      "logo3": "https://i.ibb.co/gMf1xGm/Ellipse-95-2.png",
      "logo4": "https://i.ibb.co/0f6LNd7/Ellipse-95-1.png",
       "count": "1 of 321",
       "ratio": 26.52
    },
    {
      "id": "r3t45kdf6",
       "name": "Cryptix",
      "eth": "2,769.39",
      "time": "30",
      "img": "https://media.istockphoto.com/id/1403389740/photo/bitcoin-in-recession-global-market-crisis-stock-red-price-drop-arrow-down-chart-fall-money.jpg?s=2048x2048&w=is&k=20&c=HUCt_2ym7YSUDabwkA0tEOSKm9LYpTx4YUwyLpOuN9U=",
      "logo1": "logo1.png",
      "logo2": "logo2.png",
      "logo3": "logo3.png",
      "logo4": "logo4.png",
       "count": "1 of 321",
       "ratio": 10.52
    },
    {
      "id": "bdf9gkj324",
      "name": "Frensare",
      "eth": "9,232.39",
      "time": "28",
      "img": "https://media.istockphoto.com/id/1367699775/photo/nft-non-fungible-token-golden-coins-falling-trendy-cryptocurrencies-and-coins-on-the.jpg?s=2048x2048&w=is&k=20&c=soA6I6ONJc5Ctcq6ymGVjlgE5nfLgKyMm3WfJRkd3vo=",
      "logo1": "logo1.png",
      "logo2": "logo2.png",
      "logo3": "logo3.png",
      "logo4": "logo4.png",
      "count": "1 of 321",
      "ratio": 2.52  
    },
    {
      "id": "t7h32kf4j",
      "name": "PunkArt",
      "eth": "3,7869.39",
      "time": "32",
      "img": "https://media.istockphoto.com/id/1387545129/photo/dollar-currency-secure-banking-3d-illustration-cyber-style-money-symbol.jpg?s=2048x2048&w=is&k=20&c=paLgyjw9Eh34_wgDkAAH1AQ70eN2kfpdnkDwgIeUxIY=",
      "logo1": "logo1.png",
      "logo2": "logo2.png",
      "logo3": "logo3.png",
      "logo4": "logo4.png",
      "count": "1 of 321",
       "ratio": 2.52
    },
    {
      "id": "p4k3df90g",
      "name": "Art Crypto",
      "eth": "10,769.39",
      "time": "27",
      "img": "https://media.istockphoto.com/id/941531990/photo/digital-coin-of-england.jpg?s=2048x2048&w=is&k=20&c=eFxyyjoRFQLSAEeMDiC_GFLwAZXAmI-zluuiXVEviMY=",
      "logo1": "logo1.png",
      "logo2": "logo2.png",
      "logo3": "logo3.png",
      "logo4": "logo4.png",
      "count": "1 of 321",
       "ratio": 1.52
    },
    {
      "id": "hj67b4k23",
       "name": "ArtCrypto",
      "time": "3h 50m 2s left",
      "img": "https://i.ibb.co/NVw2bGC/unsplash-p-Vo-EPp-Lw818.png",
      "img1": "https://i.ibb.co/LtdsXJg/Vector.png",
      "logo1": "logo1.png",
      "logo2": "logo2.png",
      "logo3": "logo3.png",
      "logo4": "logo4.png",
      "count": "1 of 321",
      "ratio": 0.25
    },
    {
      "id": "9b8dfgh2s",
      "name": "This NFT",
      "time": "3h 50m 2s left",
      "img": "https://i.ibb.co/bLYCYkb/unsplash-E8-Ufcyxz514.png",
       "img1": "https://i.ibb.co/LtdsXJg/Vector.png",
      "logo1": "logo1.png",
      "logo2": "logo2.png",
      "logo3": "logo3.png",
      "logo4": "logo4.png",
      "count": "1 of 321",
      "ratio": 0.12
    },
    {
      "id": "3b4k2j8dhf",
      "name": "NameCrypto",
     "time": "3h 50m 2s left",
      "img": "https://i.ibb.co/NVw2bGC/unsplash-p-Vo-EPp-Lw818.png",
      "img1": "https://i.ibb.co/LtdsXJg/Vector.png",
      "logo1": "logo1.png",
      "logo2": "logo2.png",
      "logo3": "logo3.png",
      "logo4": "logo4.png",   
      "count": "1 of 321",
      "ratio": 0.6
    },
    {
      "id": "j4kjfs83hd",
      "name": "KingCrypto",
      "time": "3h 50m 2s left",
      "img": "https://i.ibb.co/wM40BQC/unsplash-t-ZCr-Fp-SNi-IQ.png",
     "img1": "https://i.ibb.co/LtdsXJg/Vector.png",
      "logo1": "logo1.png",
      "logo2": "logo2.png",
      "logo3": "logo3.png",
      "logo4": "logo4.png",
      "count": "1 of 321",
      "ratio": 0.18
    },
    {
      "id": "4j2hfgk3l",
      "name": "ArtCrypto",
      "time": "3h 50m 2s left",
      "img": "https://i.ibb.co/sCDSSGt/unsplash-F56-Y7dgr-Akc.png",
      "img1": "https://i.ibb.co/LtdsXJg/Vector.png",
      "logo1": "logo1.png",
      "logo2": "logo2.png",
      "logo3": "logo3.png",
      "logo4": "logo4.png",
      "count": "1 of 321",
      "ratio": 0.70
    },
    {
      "id": "9j2Zfmk7l",
      "eth": "This NFT",
      "time": "3h 50m 2s left",
      "img": "https://i.ibb.co/wM40BQC/unsplash-t-ZCr-Fp-SNi-IQ.png",
       "img1": "https://i.ibb.co/LtdsXJg/Vector.png",
      "logo1": "logo1.png",
      "logo2": "logo2.png",
      "logo3": "logo3.png",
      "logo4": "logo4.png",
      "count": "1 of 321",
      "ratio": 0.51
    },
    {
      "id": "16j2hfgk3l",
      "name": "NameCrypto",
      "time": "3h 50m 2s left",
      "img": "https://i.ibb.co/NVw2bGC/unsplash-p-Vo-EPp-Lw818.png",
      "img1": "https://i.ibb.co/LtdsXJg/Vector.png",
      "logo1": "logo1.png",
      "logo2": "logo2.png",
      "logo3": "logo3.png",
      "logo4": "logo4.png",
      "count": "1 of 321",
      "ratio": 0.39
    },
    {
      "id": "28j7fhgk9d",
       "name": "KingCrypto",
      "time": "3h 50m 2s left",
      "img": "https://i.ibb.co/bLYCYkb/unsplash-E8-Ufcyxz514.png",
      "img1": "https://i.ibb.co/LtdsXJg/Vector.png",
      "logo1": "logo1.png",
      "logo2": "logo2.png",
      "logo3": "logo3.png",
      "logo4": "logo4.png",
      "count": "1 of 321",
      "ratio": 0.58
    },
    {
      "id": "4u5hfk39js",
       "name": "ArtCrypto",
      "time": "3h 50m 2s left",
      "img": "https://i.ibb.co/sCDSSGt/unsplash-F56-Y7dgr-Akc.png",
      "img1": "https://i.ibb.co/LtdsXJg/Vector.png", 
      "logo1": "logo1.png",
      "logo2": "logo2.png",
      "logo3": "logo3.png",
      "logo4": "logo4.png",
      "count": "1 of 321",
      "ratio": 0.71
    },
    {
      "id": "5jfgk3h82n",
       "name": "This NFt",
      "time": "3h 50m 2s left",
      "img": "https://i.ibb.co/NVw2bGC/unsplash-p-Vo-EPp-Lw818.png",
      "img1": "https://i.ibb.co/LtdsXJg/Vector.png",
      "logo1": "logo1.png",
      "logo2": "logo2.png",
      "logo3": "logo3.png",
      "logo4": "logo4.png",
      "count": "1 of 321",
      "ratio": 0.86
    },
    {
      "id": "3h4k7jg5t8",
       "name": "NameCrypto",
      "time": "3h 50m 2s left",
      "img": "https://i.ibb.co/wM40BQC/unsplash-t-ZCr-Fp-SNi-IQ.png",
      "img1": "https://i.ibb.co/LtdsXJg/Vector.png",
      "logo1": "logo1.png",
      "logo2": "logo2.png",
      "logo3": "logo3.png",
      "logo4": "logo4.png",
      "count": "1 of 321",
      "ratio": 0.92
    },
    {
      "id": "9j6s5kdf2g",
       "name": "KingCrypto",
      "time": "3h 50m 2s left",
      "img": "https://i.ibb.co/bLYCYkb/unsplash-E8-Ufcyxz514.png",
      "img1": "https://i.ibb.co/LtdsXJg/Vector.png",
      "logo1": "logo1.png",
      "logo2": "logo2.png",
      "logo3": "logo3.png",
      "logo4": "logo4.png",
      "count": "1 of 321",
      "ratio": 0.78
    },
    {
      "id": "2hsg7jfk4l",
      "name": "ArtCrypto",
      "time": "3h 50m 2s left",
      "img": "https://i.ibb.co/NVw2bGC/unsplash-p-Vo-EPp-Lw818.png",
      "img1": "https://i.ibb.co/LtdsXJg/Vector.png",
      "logo1": "logo1.png",
      "logo2": "logo2.png",
      "logo3": "logo3.png",
      "logo4": "logo4.png",
      "count": "1 of 321",
      "ratio": 0.67
    },
    {
      "id": "8j3gk4h9dq",
       "name": "This NFT",
      "time": "3h 50m 2s left",
      "img": "https://i.ibb.co/wM40BQC/unsplash-t-ZCr-Fp-SNi-IQ.png",
      "img1": "https://i.ibb.co/LtdsXJg/Vector.png",
      "logo1": "logo1.png",
      "logo2": "logo2.png",
      "logo3": "logo3.png",
      "logo4": "logo4.png",
      "count": "1 of 321",
      "ratio": 0.53
    },
    {
      "id": "1hf3kgj9dq",
       "name": "NameCrypto",
      "time": "3h 50m 2s left",
      "img": "https://i.ibb.co/sCDSSGt/unsplash-F56-Y7dgr-Akc.png",
      "img1": "https://i.ibb.co/LtdsXJg/Vector.png",
      "logo1": "logo1.png",
      "logo2": "logo2.png",
      "logo3": "logo3.png",
      "logo4": "logo4.png",
      "count": "1 of 321",
      "ratio": 0.43
    },
    {
      "id": "9g7k4hj3pq",
       "name": "KingCrypto",
      "time": "3h 50m 2s left",
      "img": "https://i.ibb.co/NVw2bGC/unsplash-p-Vo-EPp-Lw818.png",
      "img1": "https://i.ibb.co/LtdsXJg/Vector.png",
      "logo1": "logo1.png",
      "logo2": "logo2.png",
      "logo3": "logo3.png",
      "logo4": "logo4.png",
      "count": "1 of 321",
      "ratio": 0.63
    }
  
  ]
  